LICENSE
plotlab/__init__.py
plotlab/plotlab.py
plotlab-0.1.1.dist-info/LICENSE
plotlab-0.1.1.dist-info/WHEEL
plotlab-0.1.1.dist-info/METADATA
plotlab-0.1.1.dist-info/RECORD
