Metadata-Version: 2.1
Name: plotlab
Version: 0.1.1
Summary: Stacked plots for Python
Home-page: https://github.com/logspace-ai/plotlab
License: MIT
Author: Ibis Prevedello
Author-email: ibiscp@gmail.com
Requires-Python: >=3.8,<3.11
Classifier: License :: OSI Approved :: MIT License
Classifier: Programming Language :: Python :: 3
Classifier: Programming Language :: Python :: 3.10
Classifier: Programming Language :: Python :: 3.8
Classifier: Programming Language :: Python :: 3.9
Requires-Dist: plotly (>=5.7.0,<6.0.0)
Project-URL: Repository, https://github.com/logspace-ai/plotlab
